redbucket/__init__.py
redbucket/base.py
redbucket/codecs.py
redbucket/data.py
redbucket/in_memory.py
redbucket/py.typed
redbucket/script.py
redbucket/transactional.py
redbucket-0.1.0.dist-info/LICENSE
redbucket-0.1.0.dist-info/METADATA
redbucket-0.1.0.dist-info/WHEEL
redbucket-0.1.0.dist-info/top_level.txt
redbucket-0.1.0.dist-info/RECORD
