Metadata-Version: 2.1
Name: redbucket
Version: 0.1.0
Summary: Python rate limiting library using Redis for shared state.
Home-page: https://github.com/nickgaya/redbucket
Author: Nicholas Gaya
Author-email: nicholasgaya+pypi@gmail.com
License: MIT License
Platform: UNKNOWN
Classifier: Development Status :: 4 - Beta
Classifier: Intended Audience :: Developers
Classifier: License :: OSI Approved :: MIT License
Classifier: Operating System :: OS Independent
Classifier: Programming Language :: Python :: 3 :: Only
Classifier: Programming Language :: Python :: 3.6
Classifier: Programming Language :: Python :: 3.7
Classifier: Programming Language :: Python :: 3.8
Classifier: Topic :: Software Development :: Libraries :: Python Modules
Requires-Python: ~=3.6
Requires-Dist: redis (~=3.0)
